{
  "metadata" : {
    "identifier" : "https://nghetruyenma.net/dau-lau-co-tran.html",
    "title" : "Đầu Lâu Cổ Trấn",
    "subtitle" : "N/A",
    "author" : {
      "name" : "Nguyễn Ngọc Ngà",
      "sortAs" : ""
    },
    "narrator" : "N/A",
    "language" : "vi",
    "description" : "N/A",
    "publisher" : "N/A",
    "subject" : null,
    "modified" : null,
    "published" : "2023-06-27",
    "duration" : 4306,
    "abridged" : false,
    "conformsTo" : null,
    "numberOfPages" : null,
    "readingProgression" : null,
    "belongsTo" : null,
    "presentation" : null,
    "@type" : "http://schema.org/Audiobook",
    "schema:license" : "https://creativecommons.org/publicdomain/zero/1.0/"
  },
  "links" : [ {
    "rel" : "self",
    "href" : "https://raw.githubusercontent.com/vietduyhuynh90s/book_storage_two10/main/EPUB/EPUB_1a31b0595e603cfec23ac4e2c85411d1.json",
    "type" : "application/audiobook+json"
  }, {
    "rel" : "cover",
    "href" : "https://raw.githubusercontent.com/vietduyhuynh90s/book_storage_two10/main/IMAGE/IMAGE_1a31b0595e603cfec23ac4e2c85411d1.webp",
    "type" : "image/jpeg",
    "height" : 300,
    "width" : 300
  } ],
  "readingOrder" : [ {
    "href" : "https://archive.org/download/dau-lau-co-tran/dau-lau-co-tran.mp3",
    "type" : "audio/mpeg",
    "bitrate" : 128,
    "duration" : 4306,
    "title" : "dau-lau-co-tran",
    "properties" : null,
    "alternate" : null
  } ],
  "toc" : [ {
    "href" : "https://archive.org/download/dau-lau-co-tran/dau-lau-co-tran.mp3",
    "title" : "dau-lau-co-tran",
    "children" : [ ]
  } ],
  "@context" : "https://readium.org/webpub-manifest/context.jsonld"
}