{
  "metadata" : {
    "identifier" : "https://www.nettruyento.com/truyen-tranh/ngu-dai-do-de-cua-charlotte-257932",
    "title" : "Ngũ Đại Đồ Đệ Của Charlotte - Chapter 114",
    "subtitle" : null,
    "author" : null,
    "narrator" : null,
    "language" : "vi",
    "description" : null,
    "publisher" : "N/A",
    "subject" : null,
    "modified" : null,
    "published" : "2023-06-09",
    "duration" : 0,
    "abridged" : false,
    "conformsTo" : "https://readium.org/webpub-manifest/profiles/divina",
    "numberOfPages" : 207,
    "readingProgression" : "ttb",
    "belongsTo" : null,
    "presentation" : {
      "fit" : "width",
      "overflow" : "scrolled",
      "continuous" : true
    },
    "@type" : null,
    "schema:license" : null
  },
  "links" : [ {
    "rel" : "self",
    "href" : "https://raw.githubusercontent.com/thuvienonline40/book_storage_collection/main/comic_manifest.json",
    "type" : "application/divina+json"
  } ],
  "readingOrder" : [ {
    "href" : "https://raw.githubusercontent.com/tsvhcomic210/comic_storage10/main/IMAGE/IMAGE_25e8107379b08e1bfbe18055b8d229b5_4c9b21b3e35d0ae49d69548e908ac24e_799adb2f5d7118d6ae71cb4907953627.jpg",
    "type" : "image/jpeg",
    "bitrate" : 0,
    "duration" : 0,
    "title" : null,
    "properties" : null,
    "alternate" : [ {
      "href" : "https://i226.ntcdntempv26.com/data/images/25789/814698/001.jpg?data=net",
      "type" : "image/jpeg",
      "bitrate" : 0,
      "duration" : 0,
      "title" : null,
      "properties" : null,
      "alternate" : null
    } ]
  }, {
    "href" : "https://raw.githubusercontent.com/tsvhcomic210/comic_storage10/main/IMAGE/IMAGE_25e8107379b08e1bfbe18055b8d229b5_4c9b21b3e35d0ae49d69548e908ac24e_ba116cbfdbf942aceb3ad1819223dbbf.jpg",
    "type" : "image/jpeg",
    "bitrate" : 0,
    "duration" : 0,
    "title" : null,
    "properties" : null,
    "alternate" : [ {
      "href" : "https://i226.ntcdntempv26.com/data/images/25789/814698/002.jpg?data=net",
      "type" : "image/jpeg",
      "bitrate" : 0,
      "duration" : 0,
      "title" : null,
      "properties" : null,
      "alternate" : null
    } ]
  }, {
    "href" : "https://raw.githubusercontent.com/tsvhcomic210/comic_storage10/main/IMAGE/IMAGE_25e8107379b08e1bfbe18055b8d229b5_4c9b21b3e35d0ae49d69548e908ac24e_26fb09fbf7191268071b70c59b872d19.jpg",
    "type" : "image/jpeg",
    "bitrate" : 0,
    "duration" : 0,
    "title" : null,
    "properties" : null,
    "alternate" : [ {
      "href" : "https://i226.ntcdntempv26.com/data/images/25789/814698/003.jpg?data=net",
      "type" : "image/jpeg",
      "bitrate" : 0,
      "duration" : 0,
      "title" : null,
      "properties" : null,
      "alternate" : null
    } ]
  }, {
    "href" : "https://raw.githubusercontent.com/tsvhcomic210/comic_storage10/main/IMAGE/IMAGE_25e8107379b08e1bfbe18055b8d229b5_4c9b21b3e35d0ae49d69548e908ac24e_afe9d04d349861c5596482e2d352d2f4.jpg",
    "type" : "image/jpeg",
    "bitrate" : 0,
    "duration" : 0,
    "title" : null,
    "properties" : null,
    "alternate" : [ {
      "href" : "https://i226.ntcdntempv26.com/data/images/25789/814698/004.jpg?data=net",
      "type" : "image/jpeg",
      "bitrate" : 0,
      "duration" : 0,
      "title" : null,
      "properties" : null,
      "alternate" : null
    } ]
  }, {
    "href" : "https://raw.githubusercontent.com/tsvhcomic210/comic_storage10/main/IMAGE/IMAGE_25e8107379b08e1bfbe18055b8d229b5_4c9b21b3e35d0ae49d69548e908ac24e_5a3b77bfbe87df10be5ac01c4d452bba.jpg",
    "type" : "image/jpeg",
    "bitrate" : 0,
    "duration" : 0,
    "title" : null,
    "properties" : null,
    "alternate" : [ {
      "href" : "https://i226.ntcdntempv26.com/data/images/25789/814698/005.jpg?data=net",
      "type" : "image/jpeg",
      "bitrate" : 0,
      "duration" : 0,
      "title" : null,
      "properties" : null,
      "alternate" : null
    } ]
  }, {
    "href" : "https://raw.githubusercontent.com/tsvhcomic210/comic_storage10/main/IMAGE/IMAGE_25e8107379b08e1bfbe18055b8d229b5_4c9b21b3e35d0ae49d69548e908ac24e_faea7709a4e3690f7b93d33075f7053c.jpg",
    "type" : "image/jpeg",
    "bitrate" : 0,
    "duration" : 0,
    "title" : null,
    "properties" : null,
    "alternate" : [ {
      "href" : "https://i226.ntcdntempv26.com/data/images/25789/814698/006.jpg?data=net",
      "type" : "image/jpeg",
      "bitrate" : 0,
      "duration" : 0,
      "title" : null,
      "properties" : null,
      "alternate" : null
    } ]
  }, {
    "href" : "https://raw.githubusercontent.com/tsvhcomic210/comic_storage10/main/IMAGE/IMAGE_25e8107379b08e1bfbe18055b8d229b5_4c9b21b3e35d0ae49d69548e908ac24e_14e9f62dbec45de69b50456b18b5a559.jpg",
    "type" : "image/jpeg",
    "bitrate" : 0,
    "duration" : 0,
    "title" : null,
    "properties" : null,
    "alternate" : [ {
      "href" : "https://i226.ntcdntempv26.com/data/images/25789/814698/007.jpg?data=net",
      "type" : "image/jpeg",
      "bitrate" : 0,
      "duration" : 0,
      "title" : null,
      "properties" : null,
      "alternate" : null
    } ]
  }, {
    "href" : "https://raw.githubusercontent.com/tsvhcomic210/comic_storage10/main/IMAGE/IMAGE_25e8107379b08e1bfbe18055b8d229b5_4c9b21b3e35d0ae49d69548e908ac24e_157cc41d33d18d16fb6380b545ae75e3.jpg",
    "type" : "image/jpeg",
    "bitrate" : 0,
    "duration" : 0,
    "title" : null,
    "properties" : null,
    "alternate" : [ {
      "href" : "https://i226.ntcdntempv26.com/data/images/25789/814698/008.jpg?data=net",
      "type" : "image/jpeg",
      "bitrate" : 0,
      "duration" : 0,
      "title" : null,
      "properties" : null,
      "alternate" : null
    } ]
  }, {
    "href" : "https://raw.githubusercontent.com/tsvhcomic210/comic_storage10/main/IMAGE/IMAGE_25e8107379b08e1bfbe18055b8d229b5_4c9b21b3e35d0ae49d69548e908ac24e_5ce1b7906601c874d70961a03bd14b77.jpg",
    "type" : "image/jpeg",
    "bitrate" : 0,
    "duration" : 0,
    "title" : null,
    "properties" : null,
    "alternate" : [ {
      "href" : "https://i226.ntcdntempv26.com/data/images/25789/814698/009.jpg?data=net",
      "type" : "image/jpeg",
      "bitrate" : 0,
      "duration" : 0,
      "title" : null,
      "properties" : null,
      "alternate" : null
    } ]
  }, {
    "href" : "https://raw.githubusercontent.com/tsvhcomic210/comic_storage10/main/IMAGE/IMAGE_25e8107379b08e1bfbe18055b8d229b5_4c9b21b3e35d0ae49d69548e908ac24e_aaa09ccbf2e5ad6c0fd8ac40ba92ef77.jpg",
    "type" : "image/jpeg",
    "bitrate" : 0,
    "duration" : 0,
    "title" : null,
    "properties" : null,
    "alternate" : [ {
      "href" : "https://i226.ntcdntempv26.com/data/images/25789/814698/010.jpg?data=net",
      "type" : "image/jpeg",
      "bitrate" : 0,
      "duration" : 0,
      "title" : null,
      "properties" : null,
      "alternate" : null
    } ]
  }, {
    "href" : "https://raw.githubusercontent.com/tsvhcomic210/comic_storage10/main/IMAGE/IMAGE_25e8107379b08e1bfbe18055b8d229b5_4c9b21b3e35d0ae49d69548e908ac24e_b4da03417f8fc7a6bd266ec77a3ec764.jpg",
    "type" : "image/jpeg",
    "bitrate" : 0,
    "duration" : 0,
    "title" : null,
    "properties" : null,
    "alternate" : [ {
      "href" : "https://i226.ntcdntempv26.com/data/images/25789/814698/011.jpg?data=net",
      "type" : "image/jpeg",
      "bitrate" : 0,
      "duration" : 0,
      "title" : null,
      "properties" : null,
      "alternate" : null
    } ]
  }, {
    "href" : "https://raw.githubusercontent.com/tsvhcomic210/comic_storage10/main/IMAGE/IMAGE_25e8107379b08e1bfbe18055b8d229b5_4c9b21b3e35d0ae49d69548e908ac24e_d9debc198a6d990bff2949ed896d457d.jpg",
    "type" : "image/jpeg",
    "bitrate" : 0,
    "duration" : 0,
    "title" : null,
    "properties" : null,
    "alternate" : [ {
      "href" : "https://i226.ntcdntempv26.com/data/images/25789/814698/012.jpg?data=net",
      "type" : "image/jpeg",
      "bitrate" : 0,
      "duration" : 0,
      "title" : null,
      "properties" : null,
      "alternate" : null
    } ]
  }, {
    "href" : "https://raw.githubusercontent.com/tsvhcomic210/comic_storage10/main/IMAGE/IMAGE_25e8107379b08e1bfbe18055b8d229b5_4c9b21b3e35d0ae49d69548e908ac24e_fb20263d5ba48dc640062698ff0477a4.jpg",
    "type" : "image/jpeg",
    "bitrate" : 0,
    "duration" : 0,
    "title" : null,
    "properties" : null,
    "alternate" : [ {
      "href" : "https://i226.ntcdntempv26.com/data/images/25789/814698/013.jpg?data=net",
      "type" : "image/jpeg",
      "bitrate" : 0,
      "duration" : 0,
      "title" : null,
      "properties" : null,
      "alternate" : null
    } ]
  }, {
    "href" : "https://raw.githubusercontent.com/tsvhcomic210/comic_storage10/main/IMAGE/IMAGE_25e8107379b08e1bfbe18055b8d229b5_4c9b21b3e35d0ae49d69548e908ac24e_f09e44d1461cbf776af4dd82304bd1dd.jpg",
    "type" : "image/jpeg",
    "bitrate" : 0,
    "duration" : 0,
    "title" : null,
    "properties" : null,
    "alternate" : [ {
      "href" : "https://i226.ntcdntempv26.com/data/images/25789/814698/014.jpg?data=net",
      "type" : "image/jpeg",
      "bitrate" : 0,
      "duration" : 0,
      "title" : null,
      "properties" : null,
      "alternate" : null
    } ]
  }, {
    "href" : "https://raw.githubusercontent.com/tsvhcomic210/comic_storage10/main/IMAGE/IMAGE_25e8107379b08e1bfbe18055b8d229b5_4c9b21b3e35d0ae49d69548e908ac24e_dc212f6dbc877e7d214f548396f61178.jpg",
    "type" : "image/jpeg",
    "bitrate" : 0,
    "duration" : 0,
    "title" : null,
    "properties" : null,
    "alternate" : [ {
      "href" : "https://i226.ntcdntempv26.com/data/images/25789/814698/015.jpg?data=net",
      "type" : "image/jpeg",
      "bitrate" : 0,
      "duration" : 0,
      "title" : null,
      "properties" : null,
      "alternate" : null
    } ]
  }, {
    "href" : "https://raw.githubusercontent.com/tsvhcomic210/comic_storage10/main/IMAGE/IMAGE_25e8107379b08e1bfbe18055b8d229b5_4c9b21b3e35d0ae49d69548e908ac24e_ad2fb77b2a3cd4437cec498e4a85ff41.jpg",
    "type" : "image/jpeg",
    "bitrate" : 0,
    "duration" : 0,
    "title" : null,
    "properties" : null,
    "alternate" : [ {
      "href" : "https://i226.ntcdntempv26.com/data/images/25789/814698/016.jpg?data=net",
      "type" : "image/jpeg",
      "bitrate" : 0,
      "duration" : 0,
      "title" : null,
      "properties" : null,
      "alternate" : null
    } ]
  }, {
    "href" : "https://raw.githubusercontent.com/tsvhcomic210/comic_storage10/main/IMAGE/IMAGE_25e8107379b08e1bfbe18055b8d229b5_4c9b21b3e35d0ae49d69548e908ac24e_b9542683db28d615809d6cdd241c9004.jpg",
    "type" : "image/jpeg",
    "bitrate" : 0,
    "duration" : 0,
    "title" : null,
    "properties" : null,
    "alternate" : [ {
      "href" : "https://i226.ntcdntempv26.com/data/images/25789/814698/017.jpg?data=net",
      "type" : "image/jpeg",
      "bitrate" : 0,
      "duration" : 0,
      "title" : null,
      "properties" : null,
      "alternate" : null
    } ]
  }, {
    "href" : "https://raw.githubusercontent.com/tsvhcomic210/comic_storage10/main/IMAGE/IMAGE_25e8107379b08e1bfbe18055b8d229b5_4c9b21b3e35d0ae49d69548e908ac24e_2c40162c083068e108f5b6f80205d91e.jpg",
    "type" : "image/jpeg",
    "bitrate" : 0,
    "duration" : 0,
    "title" : null,
    "properties" : null,
    "alternate" : [ {
      "href" : "https://i226.ntcdntempv26.com/data/images/25789/814698/018.jpg?data=net",
      "type" : "image/jpeg",
      "bitrate" : 0,
      "duration" : 0,
      "title" : null,
      "properties" : null,
      "alternate" : null
    } ]
  }, {
    "href" : "https://raw.githubusercontent.com/tsvhcomic210/comic_storage10/main/IMAGE/IMAGE_25e8107379b08e1bfbe18055b8d229b5_4c9b21b3e35d0ae49d69548e908ac24e_0fafa443f823ca471673b071b45f1260.jpg",
    "type" : "image/jpeg",
    "bitrate" : 0,
    "duration" : 0,
    "title" : null,
    "properties" : null,
    "alternate" : [ {
      "href" : "https://i226.ntcdntempv26.com/data/images/25789/814698/019.jpg?data=net",
      "type" : "image/jpeg",
      "bitrate" : 0,
      "duration" : 0,
      "title" : null,
      "properties" : null,
      "alternate" : null
    } ]
  }, {
    "href" : "https://raw.githubusercontent.com/tsvhcomic210/comic_storage10/main/IMAGE/IMAGE_25e8107379b08e1bfbe18055b8d229b5_4c9b21b3e35d0ae49d69548e908ac24e_6083fc6a238cc817fabe6b1819497b2c.jpg",
    "type" : "image/jpeg",
    "bitrate" : 0,
    "duration" : 0,
    "title" : null,
    "properties" : null,
    "alternate" : [ {
      "href" : "https://i226.ntcdntempv26.com/data/images/25789/814698/020.jpg?data=net",
      "type" : "image/jpeg",
      "bitrate" : 0,
      "duration" : 0,
      "title" : null,
      "properties" : null,
      "alternate" : null
    } ]
  }, {
    "href" : "https://raw.githubusercontent.com/tsvhcomic210/comic_storage10/main/IMAGE/IMAGE_25e8107379b08e1bfbe18055b8d229b5_4c9b21b3e35d0ae49d69548e908ac24e_e6c32cd812e019b6e15a951383905630.jpg",
    "type" : "image/jpeg",
    "bitrate" : 0,
    "duration" : 0,
    "title" : null,
    "properties" : null,
    "alternate" : [ {
      "href" : "https://i226.ntcdntempv26.com/data/images/25789/814698/021.jpg?data=net",
      "type" : "image/jpeg",
      "bitrate" : 0,
      "duration" : 0,
      "title" : null,
      "properties" : null,
      "alternate" : null
    } ]
  }, {
    "href" : "https://raw.githubusercontent.com/tsvhcomic210/comic_storage10/main/IMAGE/IMAGE_25e8107379b08e1bfbe18055b8d229b5_4c9b21b3e35d0ae49d69548e908ac24e_ced879e19e0bb3713fd8383fba0897e2.jpg",
    "type" : "image/jpeg",
    "bitrate" : 0,
    "duration" : 0,
    "title" : null,
    "properties" : null,
    "alternate" : [ {
      "href" : "https://i226.ntcdntempv26.com/data/images/25789/814698/022.jpg?data=net",
      "type" : "image/jpeg",
      "bitrate" : 0,
      "duration" : 0,
      "title" : null,
      "properties" : null,
      "alternate" : null
    } ]
  }, {
    "href" : "https://raw.githubusercontent.com/tsvhcomic210/comic_storage10/main/IMAGE/IMAGE_25e8107379b08e1bfbe18055b8d229b5_4c9b21b3e35d0ae49d69548e908ac24e_e1734a6c4d693a52b47ef84c6844c97a.jpg",
    "type" : "image/jpeg",
    "bitrate" : 0,
    "duration" : 0,
    "title" : null,
    "properties" : null,
    "alternate" : [ {
      "href" : "https://i226.ntcdntempv26.com/data/images/25789/814698/023.jpg?data=net",
      "type" : "image/jpeg",
      "bitrate" : 0,
      "duration" : 0,
      "title" : null,
      "properties" : null,
      "alternate" : null
    } ]
  }, {
    "href" : "https://raw.githubusercontent.com/tsvhcomic210/comic_storage10/main/IMAGE/IMAGE_25e8107379b08e1bfbe18055b8d229b5_4c9b21b3e35d0ae49d69548e908ac24e_9de46b190f098648ed31fa647991d0f3.jpg",
    "type" : "image/jpeg",
    "bitrate" : 0,
    "duration" : 0,
    "title" : null,
    "properties" : null,
    "alternate" : [ {
      "href" : "https://i226.ntcdntempv26.com/data/images/25789/814698/024.jpg?data=net",
      "type" : "image/jpeg",
      "bitrate" : 0,
      "duration" : 0,
      "title" : null,
      "properties" : null,
      "alternate" : null
    } ]
  }, {
    "href" : "https://raw.githubusercontent.com/tsvhcomic210/comic_storage10/main/IMAGE/IMAGE_25e8107379b08e1bfbe18055b8d229b5_4c9b21b3e35d0ae49d69548e908ac24e_86c22de6ff6efe803f03c464a1adbc34.jpg",
    "type" : "image/jpeg",
    "bitrate" : 0,
    "duration" : 0,
    "title" : null,
    "properties" : null,
    "alternate" : [ {
      "href" : "https://i226.ntcdntempv26.com/data/images/25789/814698/025.jpg?data=net",
      "type" : "image/jpeg",
      "bitrate" : 0,
      "duration" : 0,
      "title" : null,
      "properties" : null,
      "alternate" : null
    } ]
  }, {
    "href" : "https://raw.githubusercontent.com/tsvhcomic210/comic_storage10/main/IMAGE/IMAGE_25e8107379b08e1bfbe18055b8d229b5_4c9b21b3e35d0ae49d69548e908ac24e_e2dd8a4a8daafcce74deac60e458706f.jpg",
    "type" : "image/jpeg",
    "bitrate" : 0,
    "duration" : 0,
    "title" : null,
    "properties" : null,
    "alternate" : [ {
      "href" : "https://i226.ntcdntempv26.com/data/images/25789/814698/026.jpg?data=net",
      "type" : "image/jpeg",
      "bitrate" : 0,
      "duration" : 0,
      "title" : null,
      "properties" : null,
      "alternate" : null
    } ]
  }, {
    "href" : "https://raw.githubusercontent.com/tsvhcomic210/comic_storage10/main/IMAGE/IMAGE_25e8107379b08e1bfbe18055b8d229b5_4c9b21b3e35d0ae49d69548e908ac24e_e7950a6e76ed0067a367f1570e4fd007.jpg",
    "type" : "image/jpeg",
    "bitrate" : 0,
    "duration" : 0,
    "title" : null,
    "properties" : null,
    "alternate" : [ {
      "href" : "https://i226.ntcdntempv26.com/data/images/25789/814698/027.jpg?data=net",
      "type" : "image/jpeg",
      "bitrate" : 0,
      "duration" : 0,
      "title" : null,
      "properties" : null,
      "alternate" : null
    } ]
  }, {
    "href" : "https://raw.githubusercontent.com/tsvhcomic210/comic_storage10/main/IMAGE/IMAGE_25e8107379b08e1bfbe18055b8d229b5_4c9b21b3e35d0ae49d69548e908ac24e_2657973f1c2156f655548f95515e3cf3.jpg",
    "type" : "image/jpeg",
    "bitrate" : 0,
    "duration" : 0,
    "title" : null,
    "properties" : null,
    "alternate" : [ {
      "href" : "https://i226.ntcdntempv26.com/data/images/25789/814698/028.jpg?data=net",
      "type" : "image/jpeg",
      "bitrate" : 0,
      "duration" : 0,
      "title" : null,
      "properties" : null,
      "alternate" : null
    } ]
  }, {
    "href" : "https://raw.githubusercontent.com/tsvhcomic210/comic_storage10/main/IMAGE/IMAGE_25e8107379b08e1bfbe18055b8d229b5_4c9b21b3e35d0ae49d69548e908ac24e_a06d8db24e182728a1dd5f723c5980cf.jpg",
    "type" : "image/jpeg",
    "bitrate" : 0,
    "duration" : 0,
    "title" : null,
    "properties" : null,
    "alternate" : [ {
      "href" : "https://i226.ntcdntempv26.com/data/images/25789/814698/029.jpg?data=net",
      "type" : "image/jpeg",
      "bitrate" : 0,
      "duration" : 0,
      "title" : null,
      "properties" : null,
      "alternate" : null
    } ]
  }, {
    "href" : "https://raw.githubusercontent.com/tsvhcomic210/comic_storage10/main/IMAGE/IMAGE_25e8107379b08e1bfbe18055b8d229b5_4c9b21b3e35d0ae49d69548e908ac24e_a0a11aa64cc53619b9a1c0f1a614fdd6.jpg",
    "type" : "image/jpeg",
    "bitrate" : 0,
    "duration" : 0,
    "title" : null,
    "properties" : null,
    "alternate" : [ {
      "href" : "https://i226.ntcdntempv26.com/data/images/25789/814698/030.jpg?data=net",
      "type" : "image/jpeg",
      "bitrate" : 0,
      "duration" : 0,
      "title" : null,
      "properties" : null,
      "alternate" : null
    } ]
  }, {
    "href" : "https://raw.githubusercontent.com/tsvhcomic210/comic_storage10/main/IMAGE/IMAGE_25e8107379b08e1bfbe18055b8d229b5_4c9b21b3e35d0ae49d69548e908ac24e_efe29b6f8622cbc2c55f1d6320980572.jpg",
    "type" : "image/jpeg",
    "bitrate" : 0,
    "duration" : 0,
    "title" : null,
    "properties" : null,
    "alternate" : [ {
      "href" : "https://i226.ntcdntempv26.com/data/images/25789/814698/031.jpg?data=net",
      "type" : "image/jpeg",
      "bitrate" : 0,
      "duration" : 0,
      "title" : null,
      "properties" : null,
      "alternate" : null
    } ]
  }, {
    "href" : "https://raw.githubusercontent.com/tsvhcomic210/comic_storage10/main/IMAGE/IMAGE_25e8107379b08e1bfbe18055b8d229b5_4c9b21b3e35d0ae49d69548e908ac24e_314a033395f23882e573d1fd53c0a839.jpg",
    "type" : "image/jpeg",
    "bitrate" : 0,
    "duration" : 0,
    "title" : null,
    "properties" : null,
    "alternate" : [ {
      "href" : "https://i226.ntcdntempv26.com/data/images/25789/814698/032.jpg?data=net",
      "type" : "image/jpeg",
      "bitrate" : 0,
      "duration" : 0,
      "title" : null,
      "properties" : null,
      "alternate" : null
    } ]
  }, {
    "href" : "https://raw.githubusercontent.com/tsvhcomic210/comic_storage10/main/IMAGE/IMAGE_25e8107379b08e1bfbe18055b8d229b5_4c9b21b3e35d0ae49d69548e908ac24e_9fd4d3cb0b71ab6155d1eee04f9fc1d2.jpg",
    "type" : "image/jpeg",
    "bitrate" : 0,
    "duration" : 0,
    "title" : null,
    "properties" : null,
    "alternate" : [ {
      "href" : "https://i226.ntcdntempv26.com/data/images/25789/814698/033.jpg?data=net",
      "type" : "image/jpeg",
      "bitrate" : 0,
      "duration" : 0,
      "title" : null,
      "properties" : null,
      "alternate" : null
    } ]
  }, {
    "href" : "https://raw.githubusercontent.com/tsvhcomic210/comic_storage10/main/IMAGE/IMAGE_25e8107379b08e1bfbe18055b8d229b5_4c9b21b3e35d0ae49d69548e908ac24e_e0642aab27e07ec83dedd577550cf2e8.jpg",
    "type" : "image/jpeg",
    "bitrate" : 0,
    "duration" : 0,
    "title" : null,
    "properties" : null,
    "alternate" : [ {
      "href" : "https://i226.ntcdntempv26.com/data/images/25789/814698/034.jpg?data=net",
      "type" : "image/jpeg",
      "bitrate" : 0,
      "duration" : 0,
      "title" : null,
      "properties" : null,
      "alternate" : null
    } ]
  }, {
    "href" : "https://raw.githubusercontent.com/tsvhcomic210/comic_storage10/main/IMAGE/IMAGE_25e8107379b08e1bfbe18055b8d229b5_4c9b21b3e35d0ae49d69548e908ac24e_58df09455856e54816d409b77c56f4d3.jpg",
    "type" : "image/jpeg",
    "bitrate" : 0,
    "duration" : 0,
    "title" : null,
    "properties" : null,
    "alternate" : [ {
      "href" : "https://i226.ntcdntempv26.com/data/images/25789/814698/035.jpg?data=net",
      "type" : "image/jpeg",
      "bitrate" : 0,
      "duration" : 0,
      "title" : null,
      "properties" : null,
      "alternate" : null
    } ]
  }, {
    "href" : "https://raw.githubusercontent.com/tsvhcomic210/comic_storage10/main/IMAGE/IMAGE_25e8107379b08e1bfbe18055b8d229b5_4c9b21b3e35d0ae49d69548e908ac24e_19d69a9979c4957ce5b3fa58592bd3f7.jpg",
    "type" : "image/jpeg",
    "bitrate" : 0,
    "duration" : 0,
    "title" : null,
    "properties" : null,
    "alternate" : [ {
      "href" : "https://i226.ntcdntempv26.com/data/images/25789/814698/036.jpg?data=net",
      "type" : "image/jpeg",
      "bitrate" : 0,
      "duration" : 0,
      "title" : null,
      "properties" : null,
      "alternate" : null
    } ]
  }, {
    "href" : "https://raw.githubusercontent.com/tsvhcomic210/comic_storage10/main/IMAGE/IMAGE_25e8107379b08e1bfbe18055b8d229b5_4c9b21b3e35d0ae49d69548e908ac24e_3ecd75f8cf74df9bcb9141dcfffefa20.jpg",
    "type" : "image/jpeg",
    "bitrate" : 0,
    "duration" : 0,
    "title" : null,
    "properties" : null,
    "alternate" : [ {
      "href" : "https://i226.ntcdntempv26.com/data/images/25789/814698/037.jpg?data=net",
      "type" : "image/jpeg",
      "bitrate" : 0,
      "duration" : 0,
      "title" : null,
      "properties" : null,
      "alternate" : null
    } ]
  }, {
    "href" : "https://raw.githubusercontent.com/tsvhcomic210/comic_storage10/main/IMAGE/IMAGE_25e8107379b08e1bfbe18055b8d229b5_4c9b21b3e35d0ae49d69548e908ac24e_8d89db631a5c0cc43d375f117227b5cd.jpg",
    "type" : "image/jpeg",
    "bitrate" : 0,
    "duration" : 0,
    "title" : null,
    "properties" : null,
    "alternate" : [ {
      "href" : "https://i226.ntcdntempv26.com/data/images/25789/814698/038.jpg?data=net",
      "type" : "image/jpeg",
      "bitrate" : 0,
      "duration" : 0,
      "title" : null,
      "properties" : null,
      "alternate" : null
    } ]
  }, {
    "href" : "https://raw.githubusercontent.com/tsvhcomic210/comic_storage10/main/IMAGE/IMAGE_25e8107379b08e1bfbe18055b8d229b5_4c9b21b3e35d0ae49d69548e908ac24e_0adbf4099f0a7666292bc1e4e40244f3.jpg",
    "type" : "image/jpeg",
    "bitrate" : 0,
    "duration" : 0,
    "title" : null,
    "properties" : null,
    "alternate" : [ {
      "href" : "https://i226.ntcdntempv26.com/data/images/25789/814698/039.jpg?data=net",
      "type" : "image/jpeg",
      "bitrate" : 0,
      "duration" : 0,
      "title" : null,
      "properties" : null,
      "alternate" : null
    } ]
  }, {
    "href" : "https://raw.githubusercontent.com/tsvhcomic210/comic_storage10/main/IMAGE/IMAGE_25e8107379b08e1bfbe18055b8d229b5_4c9b21b3e35d0ae49d69548e908ac24e_6e0ce97f234e93bc0c0b587f480e8b88.jpg",
    "type" : "image/jpeg",
    "bitrate" : 0,
    "duration" : 0,
    "title" : null,
    "properties" : null,
    "alternate" : [ {
      "href" : "https://i226.ntcdntempv26.com/data/images/25789/814698/040.jpg?data=net",
      "type" : "image/jpeg",
      "bitrate" : 0,
      "duration" : 0,
      "title" : null,
      "properties" : null,
      "alternate" : null
    } ]
  }, {
    "href" : "https://raw.githubusercontent.com/tsvhcomic210/comic_storage10/main/IMAGE/IMAGE_25e8107379b08e1bfbe18055b8d229b5_4c9b21b3e35d0ae49d69548e908ac24e_bab018d73cc53730b78ce65a0ebfb4f6.jpg",
    "type" : "image/jpeg",
    "bitrate" : 0,
    "duration" : 0,
    "title" : null,
    "properties" : null,
    "alternate" : [ {
      "href" : "https://i226.ntcdntempv26.com/data/images/25789/814698/041.jpg?data=net",
      "type" : "image/jpeg",
      "bitrate" : 0,
      "duration" : 0,
      "title" : null,
      "properties" : null,
      "alternate" : null
    } ]
  }, {
    "href" : "https://raw.githubusercontent.com/tsvhcomic210/comic_storage10/main/IMAGE/IMAGE_25e8107379b08e1bfbe18055b8d229b5_4c9b21b3e35d0ae49d69548e908ac24e_cd927cd59d7f57431d071e174e927c81.jpg",
    "type" : "image/jpeg",
    "bitrate" : 0,
    "duration" : 0,
    "title" : null,
    "properties" : null,
    "alternate" : [ {
      "href" : "https://i226.ntcdntempv26.com/data/images/25789/814698/042.jpg?data=net",
      "type" : "image/jpeg",
      "bitrate" : 0,
      "duration" : 0,
      "title" : null,
      "properties" : null,
      "alternate" : null
    } ]
  }, {
    "href" : "https://raw.githubusercontent.com/tsvhcomic210/comic_storage10/main/IMAGE/IMAGE_25e8107379b08e1bfbe18055b8d229b5_4c9b21b3e35d0ae49d69548e908ac24e_8a8b05ed3515aee5b66a728c0a453dd3.jpg",
    "type" : "image/jpeg",
    "bitrate" : 0,
    "duration" : 0,
    "title" : null,
    "properties" : null,
    "alternate" : [ {
      "href" : "https://i226.ntcdntempv26.com/data/images/25789/814698/043.jpg?data=net",
      "type" : "image/jpeg",
      "bitrate" : 0,
      "duration" : 0,
      "title" : null,
      "properties" : null,
      "alternate" : null
    } ]
  }, {
    "href" : "https://raw.githubusercontent.com/tsvhcomic210/comic_storage10/main/IMAGE/IMAGE_25e8107379b08e1bfbe18055b8d229b5_4c9b21b3e35d0ae49d69548e908ac24e_52f224389c984af0a2ce4940777d7dc8.jpg",
    "type" : "image/jpeg",
    "bitrate" : 0,
    "duration" : 0,
    "title" : null,
    "properties" : null,
    "alternate" : [ {
      "href" : "https://i226.ntcdntempv26.com/data/images/25789/814698/044.jpg?data=net",
      "type" : "image/jpeg",
      "bitrate" : 0,
      "duration" : 0,
      "title" : null,
      "properties" : null,
      "alternate" : null
    } ]
  }, {
    "href" : "https://raw.githubusercontent.com/tsvhcomic210/comic_storage10/main/IMAGE/IMAGE_25e8107379b08e1bfbe18055b8d229b5_4c9b21b3e35d0ae49d69548e908ac24e_e4ca01ce58f8ccd91cbb2ac89d76eccd.jpg",
    "type" : "image/jpeg",
    "bitrate" : 0,
    "duration" : 0,
    "title" : null,
    "properties" : null,
    "alternate" : [ {
      "href" : "https://i226.ntcdntempv26.com/data/images/25789/814698/045.jpg?data=net",
      "type" : "image/jpeg",
      "bitrate" : 0,
      "duration" : 0,
      "title" : null,
      "properties" : null,
      "alternate" : null
    } ]
  }, {
    "href" : "https://raw.githubusercontent.com/tsvhcomic210/comic_storage10/main/IMAGE/IMAGE_25e8107379b08e1bfbe18055b8d229b5_4c9b21b3e35d0ae49d69548e908ac24e_1ab3c34b3e22cdf0e06b02c5867151a8.jpg",
    "type" : "image/jpeg",
    "bitrate" : 0,
    "duration" : 0,
    "title" : null,
    "properties" : null,
    "alternate" : [ {
      "href" : "https://i226.ntcdntempv26.com/data/images/25789/814698/046.jpg?data=net",
      "type" : "image/jpeg",
      "bitrate" : 0,
      "duration" : 0,
      "title" : null,
      "properties" : null,
      "alternate" : null
    } ]
  }, {
    "href" : "https://raw.githubusercontent.com/tsvhcomic210/comic_storage10/main/IMAGE/IMAGE_25e8107379b08e1bfbe18055b8d229b5_4c9b21b3e35d0ae49d69548e908ac24e_bbddd9a5267f68a3bae493db8ce37c91.jpg",
    "type" : "image/jpeg",
    "bitrate" : 0,
    "duration" : 0,
    "title" : null,
    "properties" : null,
    "alternate" : [ {
      "href" : "https://i226.ntcdntempv26.com/data/images/25789/814698/047.jpg?data=net",
      "type" : "image/jpeg",
      "bitrate" : 0,
      "duration" : 0,
      "title" : null,
      "properties" : null,
      "alternate" : null
    } ]
  }, {
    "href" : "https://raw.githubusercontent.com/tsvhcomic210/comic_storage10/main/IMAGE/IMAGE_25e8107379b08e1bfbe18055b8d229b5_4c9b21b3e35d0ae49d69548e908ac24e_0ed5aed4e9f53c85ec1cc99ad0cec90d.jpg",
    "type" : "image/jpeg",
    "bitrate" : 0,
    "duration" : 0,
    "title" : null,
    "properties" : null,
    "alternate" : [ {
      "href" : "https://i226.ntcdntempv26.com/data/images/25789/814698/048.jpg?data=net",
      "type" : "image/jpeg",
      "bitrate" : 0,
      "duration" : 0,
      "title" : null,
      "properties" : null,
      "alternate" : null
    } ]
  }, {
    "href" : "https://raw.githubusercontent.com/tsvhcomic210/comic_storage10/main/IMAGE/IMAGE_25e8107379b08e1bfbe18055b8d229b5_4c9b21b3e35d0ae49d69548e908ac24e_eaac65ee296f594e50130745af00c4d6.jpg",
    "type" : "image/jpeg",
    "bitrate" : 0,
    "duration" : 0,
    "title" : null,
    "properties" : null,
    "alternate" : [ {
      "href" : "https://i226.ntcdntempv26.com/data/images/25789/814698/049.jpg?data=net",
      "type" : "image/jpeg",
      "bitrate" : 0,
      "duration" : 0,
      "title" : null,
      "properties" : null,
      "alternate" : null
    } ]
  }, {
    "href" : "https://raw.githubusercontent.com/tsvhcomic210/comic_storage10/main/IMAGE/IMAGE_25e8107379b08e1bfbe18055b8d229b5_4c9b21b3e35d0ae49d69548e908ac24e_10bb2cc1798042cc4b757f1d5b1d0411.jpg",
    "type" : "image/jpeg",
    "bitrate" : 0,
    "duration" : 0,
    "title" : null,
    "properties" : null,
    "alternate" : [ {
      "href" : "https://i226.ntcdntempv26.com/data/images/25789/814698/050.jpg?data=net",
      "type" : "image/jpeg",
      "bitrate" : 0,
      "duration" : 0,
      "title" : null,
      "properties" : null,
      "alternate" : null
    } ]
  }, {
    "href" : "https://raw.githubusercontent.com/tsvhcomic210/comic_storage10/main/IMAGE/IMAGE_25e8107379b08e1bfbe18055b8d229b5_4c9b21b3e35d0ae49d69548e908ac24e_fd0b63171fedb76305c9d21348451984.jpg",
    "type" : "image/jpeg",
    "bitrate" : 0,
    "duration" : 0,
    "title" : null,
    "properties" : null,
    "alternate" : [ {
      "href" : "https://i226.ntcdntempv26.com/data/images/25789/814698/051.jpg?data=net",
      "type" : "image/jpeg",
      "bitrate" : 0,
      "duration" : 0,
      "title" : null,
      "properties" : null,
      "alternate" : null
    } ]
  }, {
    "href" : "https://raw.githubusercontent.com/tsvhcomic210/comic_storage10/main/IMAGE/IMAGE_25e8107379b08e1bfbe18055b8d229b5_4c9b21b3e35d0ae49d69548e908ac24e_9d1c51551bf015ec53ffc0871647919c.jpg",
    "type" : "image/jpeg",
    "bitrate" : 0,
    "duration" : 0,
    "title" : null,
    "properties" : null,
    "alternate" : [ {
      "href" : "https://i226.ntcdntempv26.com/data/images/25789/814698/052.jpg?data=net",
      "type" : "image/jpeg",
      "bitrate" : 0,
      "duration" : 0,
      "title" : null,
      "properties" : null,
      "alternate" : null
    } ]
  }, {
    "href" : "https://raw.githubusercontent.com/tsvhcomic210/comic_storage10/main/IMAGE/IMAGE_25e8107379b08e1bfbe18055b8d229b5_4c9b21b3e35d0ae49d69548e908ac24e_7cc77c820c8fd7b1a67e158da3179642.jpg",
    "type" : "image/jpeg",
    "bitrate" : 0,
    "duration" : 0,
    "title" : null,
    "properties" : null,
    "alternate" : [ {
      "href" : "https://i226.ntcdntempv26.com/data/images/25789/814698/053.jpg?data=net",
      "type" : "image/jpeg",
      "bitrate" : 0,
      "duration" : 0,
      "title" : null,
      "properties" : null,
      "alternate" : null
    } ]
  }, {
    "href" : "https://raw.githubusercontent.com/tsvhcomic210/comic_storage10/main/IMAGE/IMAGE_25e8107379b08e1bfbe18055b8d229b5_4c9b21b3e35d0ae49d69548e908ac24e_826144dea37e478bb0e63e0d679e5f96.jpg",
    "type" : "image/jpeg",
    "bitrate" : 0,
    "duration" : 0,
    "title" : null,
    "properties" : null,
    "alternate" : [ {
      "href" : "https://i226.ntcdntempv26.com/data/images/25789/814698/054.jpg?data=net",
      "type" : "image/jpeg",
      "bitrate" : 0,
      "duration" : 0,
      "title" : null,
      "properties" : null,
      "alternate" : null
    } ]
  }, {
    "href" : "https://raw.githubusercontent.com/tsvhcomic210/comic_storage10/main/IMAGE/IMAGE_25e8107379b08e1bfbe18055b8d229b5_4c9b21b3e35d0ae49d69548e908ac24e_01df35ad7258baf8139d7b1136dafeb2.jpg",
    "type" : "image/jpeg",
    "bitrate" : 0,
    "duration" : 0,
    "title" : null,
    "properties" : null,
    "alternate" : [ {
      "href" : "https://i226.ntcdntempv26.com/data/images/25789/814698/055.jpg?data=net",
      "type" : "image/jpeg",
      "bitrate" : 0,
      "duration" : 0,
      "title" : null,
      "properties" : null,
      "alternate" : null
    } ]
  }, {
    "href" : "https://raw.githubusercontent.com/tsvhcomic210/comic_storage10/main/IMAGE/IMAGE_25e8107379b08e1bfbe18055b8d229b5_4c9b21b3e35d0ae49d69548e908ac24e_fd86c4129b519a2c9b7db7c01263ab8b.jpg",
    "type" : "image/jpeg",
    "bitrate" : 0,
    "duration" : 0,
    "title" : null,
    "properties" : null,
    "alternate" : [ {
      "href" : "https://i226.ntcdntempv26.com/data/images/25789/814698/056.jpg?data=net",
      "type" : "image/jpeg",
      "bitrate" : 0,
      "duration" : 0,
      "title" : null,
      "properties" : null,
      "alternate" : null
    } ]
  }, {
    "href" : "https://raw.githubusercontent.com/tsvhcomic210/comic_storage10/main/IMAGE/IMAGE_25e8107379b08e1bfbe18055b8d229b5_4c9b21b3e35d0ae49d69548e908ac24e_77a7845d7984515dd53b29b20d190940.jpg",
    "type" : "image/jpeg",
    "bitrate" : 0,
    "duration" : 0,
    "title" : null,
    "properties" : null,
    "alternate" : [ {
      "href" : "https://i226.ntcdntempv26.com/data/images/25789/814698/057.jpg?data=net",
      "type" : "image/jpeg",
      "bitrate" : 0,
      "duration" : 0,
      "title" : null,
      "properties" : null,
      "alternate" : null
    } ]
  }, {
    "href" : "https://raw.githubusercontent.com/tsvhcomic210/comic_storage10/main/IMAGE/IMAGE_25e8107379b08e1bfbe18055b8d229b5_4c9b21b3e35d0ae49d69548e908ac24e_ecb7e4e02980082068bb94fc7e65fb04.jpg",
    "type" : "image/jpeg",
    "bitrate" : 0,
    "duration" : 0,
    "title" : null,
    "properties" : null,
    "alternate" : [ {
      "href" : "https://i226.ntcdntempv26.com/data/images/25789/814698/058.jpg?data=net",
      "type" : "image/jpeg",
      "bitrate" : 0,
      "duration" : 0,
      "title" : null,
      "properties" : null,
      "alternate" : null
    } ]
  }, {
    "href" : "https://raw.githubusercontent.com/tsvhcomic210/comic_storage10/main/IMAGE/IMAGE_25e8107379b08e1bfbe18055b8d229b5_4c9b21b3e35d0ae49d69548e908ac24e_bcac4f9abec945b48f854ac96febec9f.jpg",
    "type" : "image/jpeg",
    "bitrate" : 0,
    "duration" : 0,
    "title" : null,
    "properties" : null,
    "alternate" : [ {
      "href" : "https://i226.ntcdntempv26.com/data/images/25789/814698/059.jpg?data=net",
      "type" : "image/jpeg",
      "bitrate" : 0,
      "duration" : 0,
      "title" : null,
      "properties" : null,
      "alternate" : null
    } ]
  }, {
    "href" : "https://raw.githubusercontent.com/tsvhcomic210/comic_storage10/main/IMAGE/IMAGE_25e8107379b08e1bfbe18055b8d229b5_4c9b21b3e35d0ae49d69548e908ac24e_f0665ce2d4a86e09e0bc139fffd00cd0.jpg",
    "type" : "image/jpeg",
    "bitrate" : 0,
    "duration" : 0,
    "title" : null,
    "properties" : null,
    "alternate" : [ {
      "href" : "https://i226.ntcdntempv26.com/data/images/25789/814698/060.jpg?data=net",
      "type" : "image/jpeg",
      "bitrate" : 0,
      "duration" : 0,
      "title" : null,
      "properties" : null,
      "alternate" : null
    } ]
  }, {
    "href" : "https://raw.githubusercontent.com/tsvhcomic210/comic_storage10/main/IMAGE/IMAGE_25e8107379b08e1bfbe18055b8d229b5_4c9b21b3e35d0ae49d69548e908ac24e_d995079891ab6ffb5a77aef6fe4e437f.jpg",
    "type" : "image/jpeg",
    "bitrate" : 0,
    "duration" : 0,
    "title" : null,
    "properties" : null,
    "alternate" : [ {
      "href" : "https://i226.ntcdntempv26.com/data/images/25789/814698/061.jpg?data=net",
      "type" : "image/jpeg",
      "bitrate" : 0,
      "duration" : 0,
      "title" : null,
      "properties" : null,
      "alternate" : null
    } ]
  }, {
    "href" : "https://raw.githubusercontent.com/tsvhcomic210/comic_storage10/main/IMAGE/IMAGE_25e8107379b08e1bfbe18055b8d229b5_4c9b21b3e35d0ae49d69548e908ac24e_72691f33afb990a0e4707a206e8acb8c.jpg",
    "type" : "image/jpeg",
    "bitrate" : 0,
    "duration" : 0,
    "title" : null,
    "properties" : null,
    "alternate" : [ {
      "href" : "https://i226.ntcdntempv26.com/data/images/25789/814698/062.jpg?data=net",
      "type" : "image/jpeg",
      "bitrate" : 0,
      "duration" : 0,
      "title" : null,
      "properties" : null,
      "alternate" : null
    } ]
  }, {
    "href" : "https://raw.githubusercontent.com/tsvhcomic210/comic_storage10/main/IMAGE/IMAGE_25e8107379b08e1bfbe18055b8d229b5_4c9b21b3e35d0ae49d69548e908ac24e_4d9af5c4c721fbc882ada7f179d05edd.jpg",
    "type" : "image/jpeg",
    "bitrate" : 0,
    "duration" : 0,
    "title" : null,
    "properties" : null,
    "alternate" : [ {
      "href" : "https://i226.ntcdntempv26.com/data/images/25789/814698/063.jpg?data=net",
      "type" : "image/jpeg",
      "bitrate" : 0,
      "duration" : 0,
      "title" : null,
      "properties" : null,
      "alternate" : null
    } ]
  }, {
    "href" : "https://raw.githubusercontent.com/tsvhcomic210/comic_storage10/main/IMAGE/IMAGE_25e8107379b08e1bfbe18055b8d229b5_4c9b21b3e35d0ae49d69548e908ac24e_3b765a1325802365e9f01229bba0b94c.jpg",
    "type" : "image/jpeg",
    "bitrate" : 0,
    "duration" : 0,
    "title" : null,
    "properties" : null,
    "alternate" : [ {
      "href" : "https://i226.ntcdntempv26.com/data/images/25789/814698/064.jpg?data=net",
      "type" : "image/jpeg",
      "bitrate" : 0,
      "duration" : 0,
      "title" : null,
      "properties" : null,
      "alternate" : null
    } ]
  }, {
    "href" : "https://raw.githubusercontent.com/tsvhcomic210/comic_storage10/main/IMAGE/IMAGE_25e8107379b08e1bfbe18055b8d229b5_4c9b21b3e35d0ae49d69548e908ac24e_9498b7e6fa2f1fdd1b5f46d0472f6d77.jpg",
    "type" : "image/jpeg",
    "bitrate" : 0,
    "duration" : 0,
    "title" : null,
    "properties" : null,
    "alternate" : [ {
      "href" : "https://i226.ntcdntempv26.com/data/images/25789/814698/065.jpg?data=net",
      "type" : "image/jpeg",
      "bitrate" : 0,
      "duration" : 0,
      "title" : null,
      "properties" : null,
      "alternate" : null
    } ]
  }, {
    "href" : "https://raw.githubusercontent.com/tsvhcomic210/comic_storage10/main/IMAGE/IMAGE_25e8107379b08e1bfbe18055b8d229b5_4c9b21b3e35d0ae49d69548e908ac24e_b78d0d41020ec5beeac456b16490fb48.jpg",
    "type" : "image/jpeg",
    "bitrate" : 0,
    "duration" : 0,
    "title" : null,
    "properties" : null,
    "alternate" : [ {
      "href" : "https://i226.ntcdntempv26.com/data/images/25789/814698/066.jpg?data=net",
      "type" : "image/jpeg",
      "bitrate" : 0,
      "duration" : 0,
      "title" : null,
      "properties" : null,
      "alternate" : null
    } ]
  }, {
    "href" : "https://raw.githubusercontent.com/tsvhcomic210/comic_storage10/main/IMAGE/IMAGE_25e8107379b08e1bfbe18055b8d229b5_4c9b21b3e35d0ae49d69548e908ac24e_0f8a10b46369ee572a21a444453adf22.jpg",
    "type" : "image/jpeg",
    "bitrate" : 0,
    "duration" : 0,
    "title" : null,
    "properties" : null,
    "alternate" : [ {
      "href" : "https://i226.ntcdntempv26.com/data/images/25789/814698/067.jpg?data=net",
      "type" : "image/jpeg",
      "bitrate" : 0,
      "duration" : 0,
      "title" : null,
      "properties" : null,
      "alternate" : null
    } ]
  }, {
    "href" : "https://raw.githubusercontent.com/tsvhcomic210/comic_storage10/main/IMAGE/IMAGE_25e8107379b08e1bfbe18055b8d229b5_4c9b21b3e35d0ae49d69548e908ac24e_f03177f73f3cc6ec416940c864ce799c.jpg",
    "type" : "image/jpeg",
    "bitrate" : 0,
    "duration" : 0,
    "title" : null,
    "properties" : null,
    "alternate" : [ {
      "href" : "https://i226.ntcdntempv26.com/data/images/25789/814698/068.jpg?data=net",
      "type" : "image/jpeg",
      "bitrate" : 0,
      "duration" : 0,
      "title" : null,
      "properties" : null,
      "alternate" : null
    } ]
  }, {
    "href" : "https://raw.githubusercontent.com/tsvhcomic210/comic_storage10/main/IMAGE/IMAGE_25e8107379b08e1bfbe18055b8d229b5_4c9b21b3e35d0ae49d69548e908ac24e_5e863aea8bbeae88d22ea1d68b514968.jpg",
    "type" : "image/jpeg",
    "bitrate" : 0,
    "duration" : 0,
    "title" : null,
    "properties" : null,
    "alternate" : [ {
      "href" : "https://i226.ntcdntempv26.com/data/images/25789/814698/069.jpg?data=net",
      "type" : "image/jpeg",
      "bitrate" : 0,
      "duration" : 0,
      "title" : null,
      "properties" : null,
      "alternate" : null
    } ]
  }, {
    "href" : "https://raw.githubusercontent.com/tsvhcomic210/comic_storage10/main/IMAGE/IMAGE_25e8107379b08e1bfbe18055b8d229b5_4c9b21b3e35d0ae49d69548e908ac24e_77a14a0d4f58bf2d404e67415c8a12d5.jpg",
    "type" : "image/jpeg",
    "bitrate" : 0,
    "duration" : 0,
    "title" : null,
    "properties" : null,
    "alternate" : [ {
      "href" : "https://i226.ntcdntempv26.com/data/images/25789/814698/070.jpg?data=net",
      "type" : "image/jpeg",
      "bitrate" : 0,
      "duration" : 0,
      "title" : null,
      "properties" : null,
      "alternate" : null
    } ]
  }, {
    "href" : "https://raw.githubusercontent.com/tsvhcomic210/comic_storage10/main/IMAGE/IMAGE_25e8107379b08e1bfbe18055b8d229b5_4c9b21b3e35d0ae49d69548e908ac24e_0a55db4d29b5f2a9408acfdcd14ea41e.jpg",
    "type" : "image/jpeg",
    "bitrate" : 0,
    "duration" : 0,
    "title" : null,
    "properties" : null,
    "alternate" : [ {
      "href" : "https://i226.ntcdntempv26.com/data/images/25789/814698/071.jpg?data=net",
      "type" : "image/jpeg",
      "bitrate" : 0,
      "duration" : 0,
      "title" : null,
      "properties" : null,
      "alternate" : null
    } ]
  }, {
    "href" : "https://raw.githubusercontent.com/tsvhcomic210/comic_storage10/main/IMAGE/IMAGE_25e8107379b08e1bfbe18055b8d229b5_4c9b21b3e35d0ae49d69548e908ac24e_9e602ed00a74cb7a2efbc4a206a1a2d7.jpg",
    "type" : "image/jpeg",
    "bitrate" : 0,
    "duration" : 0,
    "title" : null,
    "properties" : null,
    "alternate" : [ {
      "href" : "https://i226.ntcdntempv26.com/data/images/25789/814698/072.jpg?data=net",
      "type" : "image/jpeg",
      "bitrate" : 0,
      "duration" : 0,
      "title" : null,
      "properties" : null,
      "alternate" : null
    } ]
  }, {
    "href" : "https://raw.githubusercontent.com/tsvhcomic210/comic_storage10/main/IMAGE/IMAGE_25e8107379b08e1bfbe18055b8d229b5_4c9b21b3e35d0ae49d69548e908ac24e_f7db862aaf9efd718902f99ea633cef3.jpg",
    "type" : "image/jpeg",
    "bitrate" : 0,
    "duration" : 0,
    "title" : null,
    "properties" : null,
    "alternate" : [ {
      "href" : "https://i226.ntcdntempv26.com/data/images/25789/814698/073.jpg?data=net",
      "type" : "image/jpeg",
      "bitrate" : 0,
      "duration" : 0,
      "title" : null,
      "properties" : null,
      "alternate" : null
    } ]
  }, {
    "href" : "https://raw.githubusercontent.com/tsvhcomic210/comic_storage10/main/IMAGE/IMAGE_25e8107379b08e1bfbe18055b8d229b5_4c9b21b3e35d0ae49d69548e908ac24e_2a9010957c0939d6f4461e1d7abecdd2.jpg",
    "type" : "image/jpeg",
    "bitrate" : 0,
    "duration" : 0,
    "title" : null,
    "properties" : null,
    "alternate" : [ {
      "href" : "https://i226.ntcdntempv26.com/data/images/25789/814698/074.jpg?data=net",
      "type" : "image/jpeg",
      "bitrate" : 0,
      "duration" : 0,
      "title" : null,
      "properties" : null,
      "alternate" : null
    } ]
  }, {
    "href" : "https://raw.githubusercontent.com/tsvhcomic210/comic_storage10/main/IMAGE/IMAGE_25e8107379b08e1bfbe18055b8d229b5_4c9b21b3e35d0ae49d69548e908ac24e_b15678645d805d27ab11a8c17af16f40.jpg",
    "type" : "image/jpeg",
    "bitrate" : 0,
    "duration" : 0,
    "title" : null,
    "properties" : null,
    "alternate" : [ {
      "href" : "https://i226.ntcdntempv26.com/data/images/25789/814698/075.jpg?data=net",
      "type" : "image/jpeg",
      "bitrate" : 0,
      "duration" : 0,
      "title" : null,
      "properties" : null,
      "alternate" : null
    } ]
  }, {
    "href" : "https://raw.githubusercontent.com/tsvhcomic210/comic_storage10/main/IMAGE/IMAGE_25e8107379b08e1bfbe18055b8d229b5_4c9b21b3e35d0ae49d69548e908ac24e_32117073e1c9efde8cbf239ec4374508.jpg",
    "type" : "image/jpeg",
    "bitrate" : 0,
    "duration" : 0,
    "title" : null,
    "properties" : null,
    "alternate" : [ {
      "href" : "https://i226.ntcdntempv26.com/data/images/25789/814698/076.jpg?data=net",
      "type" : "image/jpeg",
      "bitrate" : 0,
      "duration" : 0,
      "title" : null,
      "properties" : null,
      "alternate" : null
    } ]
  }, {
    "href" : "https://raw.githubusercontent.com/tsvhcomic210/comic_storage10/main/IMAGE/IMAGE_25e8107379b08e1bfbe18055b8d229b5_4c9b21b3e35d0ae49d69548e908ac24e_2723f0bdb5f41d728b7f39dc094cb703.jpg",
    "type" : "image/jpeg",
    "bitrate" : 0,
    "duration" : 0,
    "title" : null,
    "properties" : null,
    "alternate" : [ {
      "href" : "https://i226.ntcdntempv26.com/data/images/25789/814698/077.jpg?data=net",
      "type" : "image/jpeg",
      "bitrate" : 0,
      "duration" : 0,
      "title" : null,
      "properties" : null,
      "alternate" : null
    } ]
  }, {
    "href" : "https://raw.githubusercontent.com/tsvhcomic210/comic_storage10/main/IMAGE/IMAGE_25e8107379b08e1bfbe18055b8d229b5_4c9b21b3e35d0ae49d69548e908ac24e_03d1bd4396066513b492cc71e0a12c1b.jpg",
    "type" : "image/jpeg",
    "bitrate" : 0,
    "duration" : 0,
    "title" : null,
    "properties" : null,
    "alternate" : [ {
      "href" : "https://i226.ntcdntempv26.com/data/images/25789/814698/078.jpg?data=net",
      "type" : "image/jpeg",
      "bitrate" : 0,
      "duration" : 0,
      "title" : null,
      "properties" : null,
      "alternate" : null
    } ]
  }, {
    "href" : "https://raw.githubusercontent.com/tsvhcomic210/comic_storage10/main/IMAGE/IMAGE_25e8107379b08e1bfbe18055b8d229b5_4c9b21b3e35d0ae49d69548e908ac24e_ffbc4a77f4dc9dd72d774adb75873587.jpg",
    "type" : "image/jpeg",
    "bitrate" : 0,
    "duration" : 0,
    "title" : null,
    "properties" : null,
    "alternate" : [ {
      "href" : "https://i226.ntcdntempv26.com/data/images/25789/814698/079.jpg?data=net",
      "type" : "image/jpeg",
      "bitrate" : 0,
      "duration" : 0,
      "title" : null,
      "properties" : null,
      "alternate" : null
    } ]
  }, {
    "href" : "https://raw.githubusercontent.com/tsvhcomic210/comic_storage10/main/IMAGE/IMAGE_25e8107379b08e1bfbe18055b8d229b5_4c9b21b3e35d0ae49d69548e908ac24e_8272eddae8b0db19961291efecad1040.jpg",
    "type" : "image/jpeg",
    "bitrate" : 0,
    "duration" : 0,
    "title" : null,
    "properties" : null,
    "alternate" : [ {
      "href" : "https://i226.ntcdntempv26.com/data/images/25789/814698/080.jpg?data=net",
      "type" : "image/jpeg",
      "bitrate" : 0,
      "duration" : 0,
      "title" : null,
      "properties" : null,
      "alternate" : null
    } ]
  } ],
  "toc" : null,
  "@context" : "https://readium.org/webpub-manifest/context.jsonld"
}